Metadata-Version: 2.4
Name: iflow-mcp_kukapay_crypto-orderbook-mcp
Version: 0.1.0
Summary: Add your description here
Requires-Python: >=3.10
License-File: LICENSE
Requires-Dist: ccxt>=4.4.78
Requires-Dist: mcp[cli]>=1.7.1
Requires-Dist: pandas>=2.2.3
Requires-Dist: tabulate>=0.9.0
Dynamic: license-file
